mrslpred/model/xgboost_final.pkl
mrslpred/motifs/motifs_0.txt
mrslpred/motifs/motifs_1.txt
mrslpred/motifs/motifs_2.txt
mrslpred/motifs/motifs_3.txt
mrslpred/motifs/motifs_4.txt
mrslpred/motifs/motifs_5.txt
mrslpred/nfeature/Nfeature_DNA.py
mrslpred/nfeature/Data/K_Mer.py
mrslpred/nfeature/Data/RDK.py
mrslpred/nfeature/Data/RDK_CT.py
mrslpred/nfeature/Data/RDK_NT.py
mrslpred/nfeature/Data/RDK_REST.py
mrslpred/nfeature/Data/RDK_SPLIT.py
mrslpred/python_scripts/__init__.py
mrslpred/python_scripts/mrslpred.py
mrslpred-1.1.dist-info/LICENSE.txt
mrslpred-1.1.dist-info/METADATA
mrslpred-1.1.dist-info/WHEEL
mrslpred-1.1.dist-info/entry_points.txt
mrslpred-1.1.dist-info/top_level.txt
mrslpred-1.1.dist-info/RECORD
