Metadata-Version: 2.1
Name: mrslpred
Version: 1.1
Summary: A tool to predict mRNA subcellular localization
Home-page: https://github.com/raghavagps/mrslpred
Requires-Python: >=3.6
License-File: LICENSE.txt
Requires-Dist: numpy
Requires-Dist: pandas
Requires-Dist: Bio
Requires-Dist: scikit-learn (==1.0.2)
Requires-Dist: xgboost (==0.90)
